yunpancli/__init__.py
yunpancli/baidu_pan_sdk.py
yunpancli/base.py
yunpancli-0.0.11.dist-info/LICENSE
yunpancli-0.0.11.dist-info/METADATA
yunpancli-0.0.11.dist-info/WHEEL
yunpancli-0.0.11.dist-info/entry_points.txt
yunpancli-0.0.11.dist-info/top_level.txt
yunpancli-0.0.11.dist-info/RECORD
