Metadata-Version: 2.1
Name: yunpancli
Version: 0.0.11
Summary: cloud storage CLI (Command Line Interface)
Home-page: https://gitee.com/aierwiki/yunpancli
Author: Tang Yubin
Author-email: tang-yu-bin@qq.com
Classifier: Programming Language :: Python :: 3
Classifier: License :: OSI Approved :: MIT License
Classifier: Operating System :: OS Independent
Requires-Python: >=3.7
License-File: LICENSE
Requires-Dist: loguru (>=0.6.0)
Requires-Dist: rich (>=4.6.0)
